AiologySimilarity/__init__.py
AiologySimilarity/main.py
aiologysimilarity-0.0.2.dist-info/METADATA
aiologysimilarity-0.0.2.dist-info/WHEEL
aiologysimilarity-0.0.2.dist-info/top_level.txt
aiologysimilarity-0.0.2.dist-info/RECORD
