Metadata-Version: 2.4
Name: AiologySimilarity
Version: 0.0.2
Summary: Subset of Aiology package
Author: Seyed Moied Seyedi (Single Star)
License: MIT
Requires-Dist: opencv-python
Requires-Dist: numpy
Requires-Dist: setuptools
Dynamic: author
Dynamic: description
Dynamic: description-content-type
Dynamic: license
Dynamic: requires-dist
Dynamic: summary
